speedx/__init__.py
speedx/cli.py
speedx/core.py
speedx/graphs.py
speedx/history.py
speedx-1.1.1.dist-info/LICENSE
speedx-1.1.1.dist-info/METADATA
speedx-1.1.1.dist-info/WHEEL
speedx-1.1.1.dist-info/entry_points.txt
speedx-1.1.1.dist-info/top_level.txt
speedx-1.1.1.dist-info/RECORD
